nclustRL/__init__.py
nclustRL/trainer.py
nclustRL/version.py
nclustRL/configs/__init__.py
nclustRL/configs/default_configs.py
nclustRL/configs/save.py
nclustRL/configs/datasets/__init__.py
nclustRL/configs/datasets/_modules.py
nclustRL/models/__init__.py
nclustRL/models/model.py
nclustRL/models/pre_train.py
nclustRL/utils/__init__.py
nclustRL/utils/errors.py
nclustRL/utils/helper.py
nclustRL/utils/plot.py
nclustRL/utils/registry.py
nclustRL/utils/type_checker.py
nclustRL/utils/typing.py
nclustRL-1.0.0.dist-info/LICENSE.md
nclustRL-1.0.0.dist-info/METADATA
nclustRL-1.0.0.dist-info/WHEEL
nclustRL-1.0.0.dist-info/top_level.txt
nclustRL-1.0.0.dist-info/RECORD
