Metadata-Version: 2.1
Name: nclustRL
Version: 1.0.0
Summary: Toolbox to learn biclustering and triclustering task using Ray's rllib and torch
Home-page: https://github.com/PedroCotovio/nclustRL
Author: Pedro Cotovio
Author-email: pgcotovio@gmail.com
License: GNU GPLv3
Project-URL: Bug Tracker, https://github.com/PedroCotovio/nclustRL/issues
Keywords: biclustring triclustering rl ray rllib torch data nclustRL
Platform: UNKNOWN
Classifier: Programming Language :: Python :: 3.8
Classifier: Programming Language :: Python :: 3.7
Classifier: License :: OSI Approved :: GNU General Public License v3 (GPLv3)
Classifier: Natural Language :: English
Classifier: Operating System :: MacOS :: MacOS X
Classifier: Operating System :: Microsoft :: Windows
Classifier: Operating System :: Unix
Classifier: Intended Audience :: Information Technology
Classifier: Intended Audience :: Science/Research
Classifier: Topic :: Scientific/Engineering :: Artificial Intelligence
Classifier: Topic :: Scientific/Engineering :: Bio-Informatics
Requires-Python: >=3.7
Requires-Dist: inquirer (>=2.7)
Requires-Dist: nclustenv (>=0.1.0)
Requires-Dist: numpy
Requires-Dist: ray (>=1.9)
Requires-Dist: scipy
Requires-Dist: seaborn
Requires-Dist: tqdm
